Metadata-Version: 1.0
Name: r12
Version: 0.2.4
Summary: Low-level interface for ST Robotics R12 robotic arm.
Home-page: https://github.com/adamheins/r12
Author: Adam Heins
Author-email: mail@adamheins.com
License: MIT
Platform: UNKNOWN
